setup.py
PBasicMaths.egg-info/PKG-INFO
PBasicMaths.egg-info/SOURCES.txt
PBasicMaths.egg-info/dependency_links.txt
PBasicMaths.egg-info/top_level.txt
PrakBasicMaths/__init__.py
PrakBasicMaths/operations.py