Metadata-Version: 2.1
Name: PBasicMaths
Version: 0.2
Summary: A Python package for basic mathematical operations
Home-page: https://github.com/SweetBunny123/PrakBasicMaths
Author: Prakrititz Borah
Author-email: Prakrititz.Borah@iiitb.ac.in
Classifier: Programming Language :: Python :: 3
Classifier: License :: OSI Approved :: MIT License
Classifier: Operating System :: OS Independent
